jax_chacha_prng.libs/libgomp-d22c30c5.so.1.0.0
jax_chacha_prng-1.4.3.dist-info/RECORD
jax_chacha_prng-1.4.3.dist-info/WHEEL
jax_chacha_prng-1.4.3.dist-info/METADATA
jax_chacha_prng-1.4.3.dist-info/top_level.txt
chacha/defs.py
chacha/cipher.py
chacha/native.pyi
chacha/native.cpython-311-aarch64-linux-gnu.so
chacha/__init__.py
chacha/version.py
chacha/jax_ops.py
chacha/random.py
