Metadata-Version: 2.1
Name: jax-chacha-prng
Version: 1.4.3
Summary: A pseudo-random number generator for JAX based on the 20 round ChaCha cipher.
Home-page: https://github.com/DPBayes/jax-chacha-prng
Author: Lukas Prediger, Aalto University
Author-email: lukas.m.prediger@aalto.fi
Classifier: Programming Language :: Python :: 3
Classifier: License :: OSI Approved :: Apache Software License
Classifier: Operating System :: POSIX :: Linux
Classifier: Operating System :: MacOS
Classifier: Development Status :: 5 - Production/Stable
Classifier: Intended Audience :: Science/Research
Classifier: Intended Audience :: Developers
Requires-Python: >=3.7
Requires-Dist: numpy<2,>=1.16
Requires-Dist: deprecation<3
Requires-Dist: jax<1.0.0,>=0.3.15
Provides-Extra: tests
Requires-Dist: jax[cpu]; extra == "tests"
Requires-Dist: pytest; extra == "tests"
Provides-Extra: compatible-jax
Requires-Dist: jax<=0.4.25,>=0.3.15; extra == "compatible-jax"
